[{"s": "oboi-kak-linoleum-dlya-sten", "t": "Обои как линолеум для стен: выбор и монтаж", "i": "📁", "c": "drugoe"}, {"s": "obuv-skripit-na-linoleume-chto-delat", "t": "Обувь скрипит на линолеуме: что делать и как устранить", "i": "👃", "c": "problemy-i-zapakh"}, {"s": "oboi-kleit-ili-linoleum-chto-snachala", "t": "Что сначала: клеить обои или стелить линолеум? Экспертный разбор", "i": "📏", "c": "tekhnologiya-ukladki"}, {"s": "oboi-linoleum-dveri-v-kakoj-posledovatelnosti", "t": "Последовательность ремонта: обои, линолеум или двери?", "i": "📏", "c": "tekhnologiya-ukladki"}, {"s": "oboi-pod-korichnevyj-linoleum-kakie-vybrat", "t": "Обои под коричневый линолеум: 15 сочетаний цветов и текстур", "i": "📁", "c": "drugoe"}, {"s": "obodrali-linoleum-chto-delat", "t": "Ободрали линолеум что делать: пошаговая инструкция и советы", "i": "🩹", "c": "remont-povrezhdenij"}, {"s": "obodralsya-linoleum-chto-delat", "t": "Ободрался линолеум: что делать и как починить своими руками", "i": "🩹", "c": "remont-povrezhdenij"}, {"s": "obratnaya-storona-linoleuma-kak-nazyvaetsya", "t": "Обратная сторона линолеума: название, структура и функции", "i": "🧐", "c": "vybor-linoleuma"}, {"s": "obshchaya-tolshchina-linoleuma-kakaya-byvaet", "t": "Общая толщина линолеума: какая бывает, таблица размеров", "i": "🧐", "c": "vybor-linoleuma"}, {"s": "obrazovalas-volna-na-linoleume-kak-ubrat", "t": "Как убрать волну на линолеуме: 5 проверенных методов", "i": "🌊", "c": "vyravnivanie-polotna"}, {"s": "obgorel-linoleum-chto-delat", "t": "Обгорел линолеум: что делать и как убрать следы", "i": "🩹", "c": "remont-povrezhdenij"}]